analysis/__init__.py
analysis/__main__.py
Topsis_Sachin_102103575-0.2.dist-info/LICENSE
Topsis_Sachin_102103575-0.2.dist-info/METADATA
Topsis_Sachin_102103575-0.2.dist-info/WHEEL
Topsis_Sachin_102103575-0.2.dist-info/entry_points.txt
Topsis_Sachin_102103575-0.2.dist-info/top_level.txt
Topsis_Sachin_102103575-0.2.dist-info/RECORD
