Metadata-Version: 2.1
Name: Topsis_Sachin_102103575
Version: 0.2
Summary: It does a topsis analysis of a given csv file
Home-page: https://github.com/Liquidator420/Topsis-Sachin-102103575
Author: Sachin Sushil Singh
Author-email: sachinsushilsingh@gmail.com
License: MIT
License-File: LICENSE
Requires-Dist: pandas
Requires-Dist: numpy
